awltelcon/__init__.py
awltelcon/__main__.py
awl_telegram_connector-0.1.dist-info/METADATA
awl_telegram_connector-0.1.dist-info/WHEEL
awl_telegram_connector-0.1.dist-info/top_level.txt
awl_telegram_connector-0.1.dist-info/RECORD
